SudokuSolver/__init__.py
SudokuSolver/solver.py
SudokuSolver/test.py
SudokuSolver-1.0.0.dist-info/LICENSE
SudokuSolver-1.0.0.dist-info/METADATA
SudokuSolver-1.0.0.dist-info/WHEEL
SudokuSolver-1.0.0.dist-info/top_level.txt
SudokuSolver-1.0.0.dist-info/RECORD
