Metadata-Version: 2.1
Name: SudokuSolver
Version: 1.0.0
Summary: sudoku solver (9X9)
Home-page: UNKNOWN
Author: Sartak Padhi
Author-email: sarthakpadhi2016@gmail.com
License: AFL-1.1
Platform: UNKNOWN
